openai_pricing_scraper/__init__.py
openai_pricing_scraper/fetch_pricing.py
openai_pricing_scraper-0.1.1.dist-info/METADATA
openai_pricing_scraper-0.1.1.dist-info/WHEEL
openai_pricing_scraper-0.1.1.dist-info/top_level.txt
openai_pricing_scraper-0.1.1.dist-info/RECORD
