Metadata-Version: 2.1
Name: openai-pricing-scraper
Version: 0.1.1
Summary: Simple way to fetch and parse the pricing data from the OpenAI pricing page.
Home-page: https://github.com/8ByteSword/openai_pricing_scraper
Author: 8ByteSword
License: UNKNOWN
Platform: UNKNOWN
Requires-Dist: beautifulsoup4
Requires-Dist: requests
